FredMD/__init__.py
FredMD/fredmd.py
FredMD/tests/__init__.py
FredMD/tests/basic_test.py
FredMD-0.0.6.dist-info/LICENSE
FredMD-0.0.6.dist-info/METADATA
FredMD-0.0.6.dist-info/WHEEL
FredMD-0.0.6.dist-info/top_level.txt
FredMD-0.0.6.dist-info/RECORD
