Metadata-Version: 2.1
Name: FredMD
Version: 0.0.6
Summary: Estimate factors off of the FRED-MD dataset
Home-page: https://github.com/joe5saia/FredMD
Author: Joe Saia
Author-email: joe5saia@gmail.com
License: UNKNOWN
Platform: UNKNOWN
Classifier: Programming Language :: Python :: 3
Classifier: License :: OSI Approved :: MIT License
Classifier: Operating System :: OS Independent
Requires-Python: >=3.6
Requires-Dist: pandas
Requires-Dist: numpy
Requires-Dist: scikit-learn
